README.rst
setup.py
django_github_hook.egg-info/PKG-INFO
django_github_hook.egg-info/SOURCES.txt
django_github_hook.egg-info/dependency_links.txt
django_github_hook.egg-info/requires.txt
django_github_hook.egg-info/top_level.txt
github_hook/__init__.py
github_hook/admin.py
github_hook/models.py
github_hook/urls.py
github_hook/views.py