Metadata-Version: 1.1
Name: django-github-hook
Version: 0.1.0
Summary: Django-powered GitHub (& Bitbucket) web hooks
Home-page: UNKNOWN
Author: S. Andrew Sheppard, Hugo Geoffroy
Author-email: andrew@wq.io
License: UNKNOWN
Platform: any
Classifier: Intended Audience :: Developers
Classifier: Programming Language :: Python
Classifier: Topic :: Software Development :: Libraries :: Python Modules
Classifier: Framework :: Django
Classifier: License :: OSI Approved :: MIT License
Classifier: Development Status :: 3 - Alpha
